pypack/SparkUtils.py
pypack/__init__.py
pypack/mission.py
pypack/spark.py
pypack/sparkUtils-old.py
pypack/spark_util.py
transform/__init__.py
transform/date_transf.py
transform/helpers.py
transform/json_transf.py
transform/type_transf.py
utils/Config.py
utils/Config_util.py
utils/Logger.py
utils/__init__.py
py_dataflow-0.0.6.dist-info/METADATA
py_dataflow-0.0.6.dist-info/WHEEL
py_dataflow-0.0.6.dist-info/top_level.txt
py_dataflow-0.0.6.dist-info/RECORD
