Metadata-Version: 2.1
Name: py-dataflow
Version: 0.0.6
Summary: PySpark application
Home-page: http://github.com/junqueira/py-dataflow
Author: junqueira
Author-email: lcjneto@gmail.com
License: UNKNOWN
Platform: UNKNOWN
Requires-Dist: flask-restful
